<?xml version="1.0" encoding="UTF-8"?>
<!-- Generated on 2025-11-21T16:20:58Z. -->
<rdf:RDF xmlns:rdf="http://www.w3.org/1999/02/22-rdf-syntax-ns#"
         xmlns:dc="http://purl.org/dc/elements/1.1/">
   <rdf:Description>
      <dc:title>Schetsen (Eerste bundel)</dc:title>
      <dc:creator>Samuel Falkland [Pseud. van Herman Heijermans (1864–1924)]</dc:creator>
      <dc:publisher>Project Gutenberg, Urbana, Illinois, USA., 2010-10-28</dc:publisher>
      <dc:date>2010-10-28</dc:date>
      <dc:rights>Dit eBoek is voor kosteloos gebruik door iedereen overal, met vrijwel geen beperkingen van welke soort dan ook. U mag het kopiëren, weggeven of hergebruiken onder de voorwaarden van de Project Gutenberg Licentie in dit eBoek of on-line op www.gutenberg.org.
Dit eBoek is geproduceerd door het on-line gedistribueerd correctieteam op www.pgdp.net.
</dc:rights>
      <dc:description>Deze schetsen van Samuel Falkland (een pseudoniem van Herman Heijermans Jr.) verschenen tussen 1894 en 1911, eerst in de Telegraaf en later in het Algemeen Dagblad. In zijn tijd waren zijn “falklandjes” net zo populair als later de “kronkels” van Simon Carmiggelt, en werden ook gebundeld uitgeven. Van deze uitgaven is dit het eerste deeltje.</dc:description>
      <dc:identifier>pg:34154</dc:identifier>
   </rdf:Description>
</rdf:RDF>
